{
  "name": "limerock/body-copy",
  "title": "Body Copy",
  "description": "Flexible rich-text content block for long-form paragraphs, headings, lists, etc.",
  "category": "text",
  "icon": "text",
  "keywords": [],
  "acf": {
    "mode": "preview",
    "renderCallback": "LimeRockTheme_block_render_callback"
  },
  "supports": {
    "className": false,
    "align": false,
    "anchor": true,
    "color": {
      "gradient": true,
      "background": true,
      "text": false
    },
    "spacing": {
      "padding": ["top", "bottom"],
      "margin": ["top", "bottom"]
    }
  },
  "example": {
    "attributes": {
      "data": {
        "is_example": true
      }
    }
  }
}
